<Namespace Name="System.Drawing">
  <Docs>
    <summary>
      <see cref="N:System.Drawing" /> 名前空間は、GDI\+ の基本的なグラフィックス機能を使用できるようにします。<see cref="N:System.Drawing.Drawing2D" />、<see cref="N:System.Drawing.Imaging" />、および <see cref="N:System.Drawing.Text" /> の各名前空間では、より高度な機能が提供されています。</summary>
    <remarks>
      <format type="text/markdown"><![CDATA[  
  
## 解説  
 <xref:System.Drawing.Graphics> クラスは、ディスプレイ デバイスに描画のためのメソッドを提供します。 などのクラス <xref:System.Drawing.Rectangle> と <xref:System.Drawing.Point> GDI \+ のプリミティブをカプセル化します。<xref:System.Drawing.Pen> クラスは、直線と曲線の抽象クラスから派生したクラスの中に、描画に使用 <xref:System.Drawing.Brush> 図形の内部を塗りつぶすために使用します。  
  
> [!CAUTION]
>  クラス内で、 <xref:System.Drawing> 名前空間は、Windows または ASP.NET サービス内での使用はサポートされません。 これらのアプリケーションの種類のいずれかの内側からこれらのクラスを使用しようと、予期しない問題が発生する可能性があります、低下しているなどのサービスのパフォーマンスと実行時の例外です。 サポートされている別の方法を参照してください。 [Windows Imaging Components](http://msdn.microsoft.com/library/windows/desktop/ee719654\(v=vs.85\).aspx)します。  
  
 ]]></format>
    </remarks>
  </Docs>
</Namespace>