<Namespace Name="System.Web.Mobile">
  <Docs>
    <summary>
      <see cref="N:System.Web.Mobile" /> 名前空間には、認証や ASP.NET モバイル Web アプリケーションを構築するために必要なエラー処理など、主要な機能が含まれています。  ASP.NET モバイル アプリケーションを開発する方法については、次を参照してください。、 [www.asp.net\/mobile](http://go.microsoft.com/fwlink/?LinkID=182900) Web サイトです。</summary>
    <remarks>
      <format type="text/markdown"><![CDATA[  
  
## 解説  
 <xref:System.Web.Mobile.MobileCapabilities> クラスは、クライアント デバイスの機能の情報にアクセスするためとデバイスの機能に対してクエリを実行するために、1 つのソースを提供します。<xref:System.Web.Mobile.MobileFormsAuthentication> クラスは、適切な認証情報を適切な Url に付加してクッキーなしのデバイスをサポートします。  
  
 ]]></format>
    </remarks>
    <altmember cref="N:System.Web.UI.MobileControls" />
    <altmember cref="N:System.Web.UI.MobileControls.Adapters" />
  </Docs>
</Namespace>